{
	"format": "BeepBox",
	"version": 9,
	"scale": "expert",
	"key": "D♯",
	"introBars": 0,
	"loopBars": 12,
	"beatsPerBar": 12,
	"ticksPerBeat": 4,
	"beatsPerMinute": 150,
	"layeredInstruments": false,
	"patternInstruments": false,
	"channels": [
		{
			"type": "pitch",
			"instruments": [
				{
					"type": "harmonics",
					"volume": 0,
					"eqFilter": [],
					"preset": 320,
					"effects": [
						"chord type",
						"note filter",
						"reverb"
					],
					"chord": "strum",
					"noteFilter": [
						{
							"type": "low-pass",
							"cutoffHz": 4756.83,
							"linearGain": 0.5
						}
					],
					"reverb": 33,
					"fadeInSeconds": 0,
					"fadeOutTicks": 48,
					"harmonics": [
						100,
						86,
						71,
						71,
						71,
						71,
						57,
						57,
						57,
						57,
						43,
						43,
						43,
						43,
						43,
						29,
						29,
						29,
						29,
						29,
						29,
						14,
						14,
						14,
						14,
						14,
						14,
						14
					],
					"unison": "none",
					"envelopes": [
						{
							"target": "noteFilterAllFreqs",
							"envelope": "twang 1"
						}
					]
				}
			],
			"patterns": [
				{
					"notes": [
						{
							"pitches": [
								55
							],
							"points": [
								{
									"tick": 0,
									"pitchBend": 0,
									"volume": 100
								},
								{
									"tick": 4,
									"pitchBend": 0,
									"volume": 100
								}
							],
							"continuesLastPattern": false
						},
						{
							"pitches": [
								54
							],
							"points": [
								{
									"tick": 4,
									"pitchBend": 0,
									"volume": 100
								},
								{
									"tick": 6,
									"pitchBend": 0,
									"volume": 100
								}
							]
						},
						{
							"pitches": [
								55
							],
							"points": [
								{
									"tick": 6,
									"pitchBend": 0,
									"volume": 100
								},
								{
									"tick": 10,
									"pitchBend": 0,
									"volume": 100
								}
							]
						},
						{
							"pitches": [
								52
							],
							"points": [
								{
									"tick": 10,
									"pitchBend": 0,
									"volume": 100
								},
								{
									"tick": 20,
									"pitchBend": 0,
									"volume": 100
								}
							]
						},
						{
							"pitches": [
								54
							],
							"points": [
								{
									"tick": 24,
									"pitchBend": 0,
									"volume": 100
								},
								{
									"tick": 28,
									"pitchBend": 0,
									"volume": 100
								}
							]
						},
						{
							"pitches": [
								53
							],
							"points": [
								{
									"tick": 28,
									"pitchBend": 0,
									"volume": 100
								},
								{
									"tick": 30,
									"pitchBend": 0,
									"volume": 100
								}
							]
						},
						{
							"pitches": [
								54
							],
							"points": [
								{
									"tick": 30,
									"pitchBend": 0,
									"volume": 100
								},
								{
									"tick": 34,
									"pitchBend": 0,
									"volume": 100
								}
							]
						},
						{
							"pitches": [
								51
							],
							"points": [
								{
									"tick": 34,
									"pitchBend": 0,
									"volume": 100
								},
								{
									"tick": 44,
									"pitchBend": 0,
									"volume": 100
								}
							]
						}
					]
				},
				{
					"notes": [
						{
							"pitches": [
								52
							],
							"points": [
								{
									"tick": 0,
									"pitchBend": 0,
									"volume": 100
								},
								{
									"tick": 4,
									"pitchBend": 0,
									"volume": 100
								}
							],
							"continuesLastPattern": false
						},
						{
							"pitches": [
								51
							],
							"points": [
								{
									"tick": 4,
									"pitchBend": 0,
									"volume": 100
								},
								{
									"tick": 6,
									"pitchBend": 0,
									"volume": 100
								}
							]
						},
						{
							"pitches": [
								52
							],
							"points": [
								{
									"tick": 6,
									"pitchBend": 0,
									"volume": 100
								},
								{
									"tick": 10,
									"pitchBend": 0,
									"volume": 100
								}
							]
						},
						{
							"pitches": [
								49
							],
							"points": [
								{
									"tick": 10,
									"pitchBend": 0,
									"volume": 100
								},
								{
									"tick": 20,
									"pitchBend": 0,
									"volume": 100
								}
							]
						},
						{
							"pitches": [
								51
							],
							"points": [
								{
									"tick": 24,
									"pitchBend": 0,
									"volume": 100
								},
								{
									"tick": 28,
									"pitchBend": 0,
									"volume": 100
								}
							]
						},
						{
							"pitches": [
								50
							],
							"points": [
								{
									"tick": 28,
									"pitchBend": 0,
									"volume": 100
								},
								{
									"tick": 30,
									"pitchBend": 0,
									"volume": 100
								}
							]
						},
						{
							"pitches": [
								51
							],
							"points": [
								{
									"tick": 30,
									"pitchBend": 0,
									"volume": 100
								},
								{
									"tick": 34,
									"pitchBend": 0,
									"volume": 100
								}
							]
						},
						{
							"pitches": [
								48
							],
							"points": [
								{
									"tick": 34,
									"pitchBend": 0,
									"volume": 100
								},
								{
									"tick": 44,
									"pitchBend": 0,
									"volume": 100
								}
							]
						}
					]
				},
				{
					"notes": [
						{
							"pitches": [
								53
							],
							"points": [
								{
									"tick": 0,
									"pitchBend": 0,
									"volume": 100
								},
								{
									"tick": 4,
									"pitchBend": 0,
									"volume": 100
								}
							],
							"continuesLastPattern": false
						},
						{
							"pitches": [
								52
							],
							"points": [
								{
									"tick": 4,
									"pitchBend": 0,
									"volume": 100
								},
								{
									"tick": 6,
									"pitchBend": 0,
									"volume": 100
								}
							]
						},
						{
							"pitches": [
								53
							],
							"points": [
								{
									"tick": 6,
									"pitchBend": 0,
									"volume": 100
								},
								{
									"tick": 10,
									"pitchBend": 0,
									"volume": 100
								}
							]
						},
						{
							"pitches": [
								55
							],
							"points": [
								{
									"tick": 10,
									"pitchBend": 0,
									"volume": 100
								},
								{
									"tick": 16,
									"pitchBend": 0,
									"volume": 100
								}
							]
						},
						{
							"pitches": [
								53
							],
							"points": [
								{
									"tick": 16,
									"pitchBend": 0,
									"volume": 100
								},
								{
									"tick": 18,
									"pitchBend": 0,
									"volume": 100
								}
							]
						},
						{
							"pitches": [
								52
							],
							"points": [
								{
									"tick": 18,
									"pitchBend": 0,
									"volume": 100
								},
								{
									"tick": 20,
									"pitchBend": 0,
									"volume": 100
								}
							]
						},
						{
							"pitches": [
								52
							],
							"points": [
								{
									"tick": 24,
									"pitchBend": 0,
									"volume": 100
								},
								{
									"tick": 28,
									"pitchBend": 0,
									"volume": 100
								}
							]
						},
						{
							"pitches": [
								51
							],
							"points": [
								{
									"tick": 28,
									"pitchBend": 0,
									"volume": 100
								},
								{
									"tick": 30,
									"pitchBend": 0,
									"volume": 100
								}
							]
						},
						{
							"pitches": [
								52
							],
							"points": [
								{
									"tick": 30,
									"pitchBend": 0,
									"volume": 100
								},
								{
									"tick": 34,
									"pitchBend": 0,
									"volume": 100
								}
							]
						},
						{
							"pitches": [
								54
							],
							"points": [
								{
									"tick": 34,
									"pitchBend": 0,
									"volume": 100
								},
								{
									"tick": 40,
									"pitchBend": 0,
									"volume": 100
								}
							]
						},
						{
							"pitches": [
								52
							],
							"points": [
								{
									"tick": 40,
									"pitchBend": 0,
									"volume": 100
								},
								{
									"tick": 42,
									"pitchBend": 0,
									"volume": 100
								}
							]
						},
						{
							"pitches": [
								51
							],
							"points": [
								{
									"tick": 42,
									"pitchBend": 0,
									"volume": 100
								},
								{
									"tick": 44,
									"pitchBend": 0,
									"volume": 100
								}
							]
						}
					]
				},
				{
					"notes": [
						{
							"pitches": [
								50
							],
							"points": [
								{
									"tick": 0,
									"pitchBend": 0,
									"volume": 100
								},
								{
									"tick": 4,
									"pitchBend": 0,
									"volume": 100
								}
							],
							"continuesLastPattern": false
						},
						{
							"pitches": [
								49
							],
							"points": [
								{
									"tick": 4,
									"pitchBend": 0,
									"volume": 100
								},
								{
									"tick": 6,
									"pitchBend": 0,
									"volume": 100
								}
							]
						},
						{
							"pitches": [
								50
							],
							"points": [
								{
									"tick": 6,
									"pitchBend": 0,
									"volume": 100
								},
								{
									"tick": 10,
									"pitchBend": 0,
									"volume": 100
								}
							]
						},
						{
							"pitches": [
								52
							],
							"points": [
								{
									"tick": 10,
									"pitchBend": 0,
									"volume": 100
								},
								{
									"tick": 16,
									"pitchBend": 0,
									"volume": 100
								}
							]
						},
						{
							"pitches": [
								50
							],
							"points": [
								{
									"tick": 16,
									"pitchBend": 0,
									"volume": 100
								},
								{
									"tick": 18,
									"pitchBend": 0,
									"volume": 100
								}
							]
						},
						{
							"pitches": [
								49
							],
							"points": [
								{
									"tick": 18,
									"pitchBend": 0,
									"volume": 100
								},
								{
									"tick": 20,
									"pitchBend": 0,
									"volume": 100
								}
							]
						},
						{
							"pitches": [
								49
							],
							"points": [
								{
									"tick": 24,
									"pitchBend": 0,
									"volume": 100
								},
								{
									"tick": 28,
									"pitchBend": 0,
									"volume": 100
								}
							]
						},
						{
							"pitches": [
								48
							],
							"points": [
								{
									"tick": 28,
									"pitchBend": 0,
									"volume": 100
								},
								{
									"tick": 30,
									"pitchBend": 0,
									"volume": 100
								}
							]
						},
						{
							"pitches": [
								49
							],
							"points": [
								{
									"tick": 30,
									"pitchBend": 0,
									"volume": 100
								},
								{
									"tick": 34,
									"pitchBend": 0,
									"volume": 100
								}
							]
						},
						{
							"pitches": [
								51
							],
							"points": [
								{
									"tick": 34,
									"pitchBend": 0,
									"volume": 100
								},
								{
									"tick": 40,
									"pitchBend": 0,
									"volume": 100
								}
							]
						},
						{
							"pitches": [
								49
							],
							"points": [
								{
									"tick": 40,
									"pitchBend": 0,
									"volume": 100
								},
								{
									"tick": 42,
									"pitchBend": 0,
									"volume": 100
								}
							]
						},
						{
							"pitches": [
								48
							],
							"points": [
								{
									"tick": 42,
									"pitchBend": 0,
									"volume": 100
								},
								{
									"tick": 44,
									"pitchBend": 0,
									"volume": 100
								}
							]
						},
						{
							"pitches": [
								51
							],
							"points": [
								{
									"tick": 45,
									"pitchBend": 0,
									"volume": 100
								},
								{
									"tick": 46,
									"pitchBend": 0,
									"volume": 100
								}
							]
						},
						{
							"pitches": [
								53
							],
							"points": [
								{
									"tick": 46,
									"pitchBend": 0,
									"volume": 100
								},
								{
									"tick": 47,
									"pitchBend": 0,
									"volume": 100
								}
							]
						},
						{
							"pitches": [
								54
							],
							"points": [
								{
									"tick": 47,
									"pitchBend": 0,
									"volume": 100
								},
								{
									"tick": 48,
									"pitchBend": 0,
									"volume": 100
								}
							]
						}
					]
				}
			],
			"sequence": [
				1,
				2,
				1,
				2,
				3,
				4,
				1,
				2,
				1,
				2,
				3,
				4
			],
			"octaveScrollBar": 3
		},
		{
			"type": "pitch",
			"instruments": [
				{
					"type": "FM",
					"volume": 0,
					"eqFilter": [],
					"preset": 203,
					"effects": [
						"vibrato",
						"note filter",
						"reverb"
					],
					"vibrato": "delayed",
					"noteFilter": [
						{
							"type": "low-pass",
							"cutoffHz": 3363.59,
							"linearGain": 0.5
						}
					],
					"reverb": 33,
					"fadeInSeconds": 0,
					"fadeOutTicks": 48,
					"algorithm": "1 2 3 4",
					"feedbackType": "1⟲ 2⟲ 3⟲ 4⟲",
					"feedbackAmplitude": 4,
					"operators": [
						{
							"frequency": "1×",
							"amplitude": 10
						},
						{
							"frequency": "3×",
							"amplitude": 7
						},
						{
							"frequency": "6×",
							"amplitude": 4
						},
						{
							"frequency": "13×",
							"amplitude": 4
						}
					],
					"envelopes": [
						{
							"target": "noteFilterAllFreqs",
							"envelope": "twang 2"
						},
						{
							"target": "feedbackAmplitude",
							"envelope": "twang 1"
						}
					]
				}
			],
			"patterns": [
				{
					"notes": [
						{
							"pitches": [
								30
							],
							"points": [
								{
									"tick": 0,
									"pitchBend": 0,
									"volume": 100
								},
								{
									"tick": 4,
									"pitchBend": 0,
									"volume": 100
								}
							],
							"continuesLastPattern": false
						},
						{
							"pitches": [
								31
							],
							"points": [
								{
									"tick": 4,
									"pitchBend": 0,
									"volume": 100
								},
								{
									"tick": 8,
									"pitchBend": 0,
									"volume": 100
								}
							]
						},
						{
							"pitches": [
								32
							],
							"points": [
								{
									"tick": 8,
									"pitchBend": 0,
									"volume": 100
								},
								{
									"tick": 12,
									"pitchBend": 0,
									"volume": 100
								}
							]
						},
						{
							"pitches": [
								29
							],
							"points": [
								{
									"tick": 24,
									"pitchBend": 0,
									"volume": 100
								},
								{
									"tick": 28,
									"pitchBend": 0,
									"volume": 100
								}
							]
						},
						{
							"pitches": [
								30
							],
							"points": [
								{
									"tick": 28,
									"pitchBend": 0,
									"volume": 100
								},
								{
									"tick": 32,
									"pitchBend": 0,
									"volume": 100
								}
							]
						},
						{
							"pitches": [
								31
							],
							"points": [
								{
									"tick": 32,
									"pitchBend": 0,
									"volume": 100
								},
								{
									"tick": 36,
									"pitchBend": 0,
									"volume": 100
								}
							]
						}
					]
				},
				{
					"notes": [
						{
							"pitches": [
								28
							],
							"points": [
								{
									"tick": 0,
									"pitchBend": 0,
									"volume": 100
								},
								{
									"tick": 4,
									"pitchBend": 0,
									"volume": 100
								}
							],
							"continuesLastPattern": false
						},
						{
							"pitches": [
								29
							],
							"points": [
								{
									"tick": 4,
									"pitchBend": 0,
									"volume": 100
								},
								{
									"tick": 8,
									"pitchBend": 0,
									"volume": 100
								}
							]
						},
						{
							"pitches": [
								30
							],
							"points": [
								{
									"tick": 8,
									"pitchBend": 0,
									"volume": 100
								},
								{
									"tick": 12,
									"pitchBend": 0,
									"volume": 100
								}
							]
						},
						{
							"pitches": [
								27
							],
							"points": [
								{
									"tick": 24,
									"pitchBend": 0,
									"volume": 100
								},
								{
									"tick": 28,
									"pitchBend": 0,
									"volume": 100
								}
							]
						},
						{
							"pitches": [
								28
							],
							"points": [
								{
									"tick": 28,
									"pitchBend": 0,
									"volume": 100
								},
								{
									"tick": 32,
									"pitchBend": 0,
									"volume": 100
								}
							]
						},
						{
							"pitches": [
								29
							],
							"points": [
								{
									"tick": 32,
									"pitchBend": 0,
									"volume": 100
								},
								{
									"tick": 36,
									"pitchBend": 0,
									"volume": 100
								}
							]
						}
					]
				},
				{
					"notes": [
						{
							"pitches": [
								41
							],
							"points": [
								{
									"tick": 0,
									"pitchBend": 0,
									"volume": 100
								},
								{
									"tick": 2,
									"pitchBend": 0,
									"volume": 100
								}
							],
							"continuesLastPattern": false
						},
						{
							"pitches": [
								41
							],
							"points": [
								{
									"tick": 2,
									"pitchBend": 0,
									"volume": 100
								},
								{
									"tick": 4,
									"pitchBend": 0,
									"volume": 100
								}
							]
						},
						{
							"pitches": [
								40
							],
							"points": [
								{
									"tick": 4,
									"pitchBend": 0,
									"volume": 100
								},
								{
									"tick": 6,
									"pitchBend": 0,
									"volume": 100
								}
							]
						},
						{
							"pitches": [
								40
							],
							"points": [
								{
									"tick": 6,
									"pitchBend": 0,
									"volume": 100
								},
								{
									"tick": 8,
									"pitchBend": 0,
									"volume": 100
								}
							]
						},
						{
							"pitches": [
								38
							],
							"points": [
								{
									"tick": 8,
									"pitchBend": 0,
									"volume": 100
								},
								{
									"tick": 10,
									"pitchBend": 0,
									"volume": 100
								}
							]
						},
						{
							"pitches": [
								38
							],
							"points": [
								{
									"tick": 10,
									"pitchBend": 0,
									"volume": 100
								},
								{
									"tick": 12,
									"pitchBend": 0,
									"volume": 100
								}
							]
						},
						{
							"pitches": [
								36
							],
							"points": [
								{
									"tick": 12,
									"pitchBend": 0,
									"volume": 100
								},
								{
									"tick": 14,
									"pitchBend": 0,
									"volume": 100
								}
							]
						},
						{
							"pitches": [
								36
							],
							"points": [
								{
									"tick": 14,
									"pitchBend": 0,
									"volume": 100
								},
								{
									"tick": 16,
									"pitchBend": 0,
									"volume": 100
								}
							]
						},
						{
							"pitches": [
								46
							],
							"points": [
								{
									"tick": 16,
									"pitchBend": 0,
									"volume": 100
								},
								{
									"tick": 18,
									"pitchBend": 0,
									"volume": 100
								}
							]
						},
						{
							"pitches": [
								45
							],
							"points": [
								{
									"tick": 18,
									"pitchBend": 0,
									"volume": 100
								},
								{
									"tick": 20,
									"pitchBend": 0,
									"volume": 100
								}
							]
						},
						{
							"pitches": [
								40
							],
							"points": [
								{
									"tick": 24,
									"pitchBend": 0,
									"volume": 100
								},
								{
									"tick": 26,
									"pitchBend": 0,
									"volume": 100
								}
							]
						},
						{
							"pitches": [
								40
							],
							"points": [
								{
									"tick": 26,
									"pitchBend": 0,
									"volume": 100
								},
								{
									"tick": 28,
									"pitchBend": 0,
									"volume": 100
								}
							]
						},
						{
							"pitches": [
								39
							],
							"points": [
								{
									"tick": 28,
									"pitchBend": 0,
									"volume": 100
								},
								{
									"tick": 30,
									"pitchBend": 0,
									"volume": 100
								}
							]
						},
						{
							"pitches": [
								39
							],
							"points": [
								{
									"tick": 30,
									"pitchBend": 0,
									"volume": 100
								},
								{
									"tick": 32,
									"pitchBend": 0,
									"volume": 100
								}
							]
						},
						{
							"pitches": [
								37
							],
							"points": [
								{
									"tick": 32,
									"pitchBend": 0,
									"volume": 100
								},
								{
									"tick": 34,
									"pitchBend": 0,
									"volume": 100
								}
							]
						},
						{
							"pitches": [
								37
							],
							"points": [
								{
									"tick": 34,
									"pitchBend": 0,
									"volume": 100
								},
								{
									"tick": 36,
									"pitchBend": 0,
									"volume": 100
								}
							]
						},
						{
							"pitches": [
								35
							],
							"points": [
								{
									"tick": 36,
									"pitchBend": 0,
									"volume": 100
								},
								{
									"tick": 38,
									"pitchBend": 0,
									"volume": 100
								}
							]
						},
						{
							"pitches": [
								35
							],
							"points": [
								{
									"tick": 38,
									"pitchBend": 0,
									"volume": 100
								},
								{
									"tick": 40,
									"pitchBend": 0,
									"volume": 100
								}
							]
						},
						{
							"pitches": [
								45
							],
							"points": [
								{
									"tick": 40,
									"pitchBend": 0,
									"volume": 100
								},
								{
									"tick": 42,
									"pitchBend": 0,
									"volume": 100
								}
							]
						},
						{
							"pitches": [
								44
							],
							"points": [
								{
									"tick": 42,
									"pitchBend": 0,
									"volume": 100
								},
								{
									"tick": 44,
									"pitchBend": 0,
									"volume": 100
								}
							]
						}
					]
				},
				{
					"notes": [
						{
							"pitches": [
								38
							],
							"points": [
								{
									"tick": 0,
									"pitchBend": 0,
									"volume": 100
								},
								{
									"tick": 2,
									"pitchBend": 0,
									"volume": 100
								}
							],
							"continuesLastPattern": false
						},
						{
							"pitches": [
								38
							],
							"points": [
								{
									"tick": 2,
									"pitchBend": 0,
									"volume": 100
								},
								{
									"tick": 4,
									"pitchBend": 0,
									"volume": 100
								}
							]
						},
						{
							"pitches": [
								37
							],
							"points": [
								{
									"tick": 4,
									"pitchBend": 0,
									"volume": 100
								},
								{
									"tick": 6,
									"pitchBend": 0,
									"volume": 100
								}
							]
						},
						{
							"pitches": [
								37
							],
							"points": [
								{
									"tick": 6,
									"pitchBend": 0,
									"volume": 100
								},
								{
									"tick": 8,
									"pitchBend": 0,
									"volume": 100
								}
							]
						},
						{
							"pitches": [
								35
							],
							"points": [
								{
									"tick": 8,
									"pitchBend": 0,
									"volume": 100
								},
								{
									"tick": 10,
									"pitchBend": 0,
									"volume": 100
								}
							]
						},
						{
							"pitches": [
								35
							],
							"points": [
								{
									"tick": 10,
									"pitchBend": 0,
									"volume": 100
								},
								{
									"tick": 12,
									"pitchBend": 0,
									"volume": 100
								}
							]
						},
						{
							"pitches": [
								33
							],
							"points": [
								{
									"tick": 12,
									"pitchBend": 0,
									"volume": 100
								},
								{
									"tick": 14,
									"pitchBend": 0,
									"volume": 100
								}
							]
						},
						{
							"pitches": [
								33
							],
							"points": [
								{
									"tick": 14,
									"pitchBend": 0,
									"volume": 100
								},
								{
									"tick": 16,
									"pitchBend": 0,
									"volume": 100
								}
							]
						},
						{
							"pitches": [
								43
							],
							"points": [
								{
									"tick": 16,
									"pitchBend": 0,
									"volume": 100
								},
								{
									"tick": 18,
									"pitchBend": 0,
									"volume": 100
								}
							]
						},
						{
							"pitches": [
								42
							],
							"points": [
								{
									"tick": 18,
									"pitchBend": 0,
									"volume": 100
								},
								{
									"tick": 20,
									"pitchBend": 0,
									"volume": 100
								}
							]
						},
						{
							"pitches": [
								37
							],
							"points": [
								{
									"tick": 24,
									"pitchBend": 0,
									"volume": 100
								},
								{
									"tick": 26,
									"pitchBend": 0,
									"volume": 100
								}
							]
						},
						{
							"pitches": [
								37
							],
							"points": [
								{
									"tick": 26,
									"pitchBend": 0,
									"volume": 100
								},
								{
									"tick": 28,
									"pitchBend": 0,
									"volume": 100
								}
							]
						},
						{
							"pitches": [
								36
							],
							"points": [
								{
									"tick": 28,
									"pitchBend": 0,
									"volume": 100
								},
								{
									"tick": 30,
									"pitchBend": 0,
									"volume": 100
								}
							]
						},
						{
							"pitches": [
								36
							],
							"points": [
								{
									"tick": 30,
									"pitchBend": 0,
									"volume": 100
								},
								{
									"tick": 32,
									"pitchBend": 0,
									"volume": 100
								}
							]
						},
						{
							"pitches": [
								34
							],
							"points": [
								{
									"tick": 32,
									"pitchBend": 0,
									"volume": 100
								},
								{
									"tick": 34,
									"pitchBend": 0,
									"volume": 100
								}
							]
						},
						{
							"pitches": [
								34
							],
							"points": [
								{
									"tick": 34,
									"pitchBend": 0,
									"volume": 100
								},
								{
									"tick": 36,
									"pitchBend": 0,
									"volume": 100
								}
							]
						},
						{
							"pitches": [
								32
							],
							"points": [
								{
									"tick": 36,
									"pitchBend": 0,
									"volume": 100
								},
								{
									"tick": 38,
									"pitchBend": 0,
									"volume": 100
								}
							]
						},
						{
							"pitches": [
								32
							],
							"points": [
								{
									"tick": 38,
									"pitchBend": 0,
									"volume": 100
								},
								{
									"tick": 40,
									"pitchBend": 0,
									"volume": 100
								}
							]
						},
						{
							"pitches": [
								42
							],
							"points": [
								{
									"tick": 40,
									"pitchBend": 0,
									"volume": 100
								},
								{
									"tick": 42,
									"pitchBend": 0,
									"volume": 100
								}
							]
						},
						{
							"pitches": [
								41
							],
							"points": [
								{
									"tick": 42,
									"pitchBend": 0,
									"volume": 100
								},
								{
									"tick": 44,
									"pitchBend": 0,
									"volume": 100
								}
							]
						}
					]
				}
			],
			"sequence": [
				1,
				2,
				1,
				2,
				3,
				4,
				1,
				2,
				1,
				2,
				3,
				4
			],
			"octaveScrollBar": 2
		},
		{
			"type": "pitch",
			"instruments": [
				{
					"type": "FM",
					"volume": -20,
					"eqFilter": [],
					"preset": 773,
					"effects": [
						"vibrato",
						"reverb"
					],
					"vibrato": "light",
					"reverb": 33,
					"fadeInSeconds": 0.0263,
					"fadeOutTicks": -3,
					"algorithm": "1←(2 3 4)",
					"feedbackType": "1⟲",
					"feedbackAmplitude": 3,
					"operators": [
						{
							"frequency": "4×",
							"amplitude": 15
						},
						{
							"frequency": "1×",
							"amplitude": 8
						},
						{
							"frequency": "1×",
							"amplitude": 0
						},
						{
							"frequency": "1×",
							"amplitude": 0
						}
					],
					"envelopes": []
				}
			],
			"patterns": [
				{
					"notes": [
						{
							"pitches": [
								43
							],
							"points": [
								{
									"tick": 12,
									"pitchBend": 0,
									"volume": 100
								},
								{
									"tick": 14,
									"pitchBend": 0,
									"volume": 100
								}
							]
						},
						{
							"pitches": [
								45
							],
							"points": [
								{
									"tick": 14,
									"pitchBend": 0,
									"volume": 100
								},
								{
									"tick": 16,
									"pitchBend": 0,
									"volume": 100
								}
							]
						},
						{
							"pitches": [
								47
							],
							"points": [
								{
									"tick": 16,
									"pitchBend": 0,
									"volume": 100
								},
								{
									"tick": 24,
									"pitchBend": 0,
									"volume": 100
								}
							]
						},
						{
							"pitches": [
								42
							],
							"points": [
								{
									"tick": 36,
									"pitchBend": 0,
									"volume": 100
								},
								{
									"tick": 38,
									"pitchBend": 0,
									"volume": 100
								}
							]
						},
						{
							"pitches": [
								44
							],
							"points": [
								{
									"tick": 38,
									"pitchBend": 0,
									"volume": 100
								},
								{
									"tick": 40,
									"pitchBend": 0,
									"volume": 100
								}
							]
						},
						{
							"pitches": [
								46
							],
							"points": [
								{
									"tick": 40,
									"pitchBend": 0,
									"volume": 100
								},
								{
									"tick": 48,
									"pitchBend": 0,
									"volume": 100
								}
							]
						}
					]
				},
				{
					"notes": [
						{
							"pitches": [
								40
							],
							"points": [
								{
									"tick": 12,
									"pitchBend": 0,
									"volume": 100
								},
								{
									"tick": 14,
									"pitchBend": 0,
									"volume": 100
								}
							]
						},
						{
							"pitches": [
								42
							],
							"points": [
								{
									"tick": 14,
									"pitchBend": 0,
									"volume": 100
								},
								{
									"tick": 16,
									"pitchBend": 0,
									"volume": 100
								}
							]
						},
						{
							"pitches": [
								44
							],
							"points": [
								{
									"tick": 16,
									"pitchBend": 0,
									"volume": 100
								},
								{
									"tick": 24,
									"pitchBend": 0,
									"volume": 100
								}
							]
						},
						{
							"pitches": [
								39
							],
							"points": [
								{
									"tick": 36,
									"pitchBend": 0,
									"volume": 100
								},
								{
									"tick": 38,
									"pitchBend": 0,
									"volume": 100
								}
							]
						},
						{
							"pitches": [
								41
							],
							"points": [
								{
									"tick": 38,
									"pitchBend": 0,
									"volume": 100
								},
								{
									"tick": 40,
									"pitchBend": 0,
									"volume": 100
								}
							]
						},
						{
							"pitches": [
								43
							],
							"points": [
								{
									"tick": 40,
									"pitchBend": 0,
									"volume": 100
								},
								{
									"tick": 48,
									"pitchBend": 0,
									"volume": 100
								}
							]
						}
					]
				},
				{
					"notes": []
				},
				{
					"notes": []
				}
			],
			"sequence": [
				1,
				2,
				1,
				2,
				0,
				0,
				1,
				2,
				1,
				2,
				0,
				0
			],
			"octaveScrollBar": 1
		}
	]
}