{
    "0":{
        "dialogue":{
            "message":"Oh yeah, I think Wally needed your help. Could you go and talk to her? She lives in the general store north-east of the inn.",
            "option1":"I'll go help her!"
        },
        "tasks":[
            {
                "id":"dialogue",
                "option":"option1",
                "questStage":1
            }
        ]
    },
    "1":{
        "dialogue":{},
        "tasks":[
            {
                "id":"npc",
                "name":"Wally"
            }
        ],
        "questStage":1
    },
    "2":{
        "dialogue":{
            "message":"Hey, thanks for coming. My parents have gone on a business trip to Seashell Village, but its been a month and they haven't returned yet. Could you go search for them?",
            "option1":"Sure!"
        },
        "tasks":[
            {
                "id":"dialogue",
                "option":"option1",
                "questStage":1
            }
        ]
    },
    "3":{
        "dialogue":{
            "message":"I forgot where Seashell Village was though. Head to the Altoris Mapmakers Lodge, Fleita knows where it is. The lodge is south-west from here.",
            "option1":"Thanks for the tip!"
        },
        "tasks":[
            {
                "id":"dialogue",
                "option":"option1",
                "questStage":1
            }
        ]
    },
    "4":{
        "dialogue":{},
        "tasks":[
            {
                "id":"npc",
                "name":"Fleita"
            }
        ],
        "questStage":1
    },
    "5":{
        "dialogue":{
            "message":"What do you want to learn about?",
            "option1":"Seashell Village"
        },
        "tasks":[
            {
                "id":"dialogue",
                "option":"option1",
                "questStage":1
            }
        ]
    },
    "6":{
        "dialogue":{
            "message":"Yes, Seashell Village is a small fishing town in Seashore Province. You can cross the bridge out of Altoris Island, and then head east to arrive at Seashell Village.",
            "option1":"Great! Now I know where to go."
        },
        "tasks":[
            {
                "id":"dialogue",
                "option":"option1",
                "questStage":1
            }
        ]
    },
    "7":{
        "dialogue":{
            "message":"Just be careful. In Seashore Province, there are a lot of monsters.",
            "option1":"I'll be extremely careful!"
        },
        "tasks":[
            {
                "id":"dialogue",
                "option":"option1",
                "triggers":"completeQuest"
            }
        ]
    }
}